cloudvault_discovery/__init__.py
cloudvault_discovery/cli.py
cloudvault_discovery/core/__init__.py
cloudvault_discovery/core/advanced.py
cloudvault_discovery/core/cert_stream.py
cloudvault_discovery/core/config.py
cloudvault_discovery/core/database.py
cloudvault_discovery/core/downloader.py
cloudvault_discovery/core/exploiter.py
cloudvault_discovery/core/forensics.py
cloudvault_discovery/core/metadata.py
cloudvault_discovery/core/network.py
cloudvault_discovery/core/permutations.py
cloudvault_discovery/core/pivoting.py
cloudvault_discovery/core/queue_manager.py
cloudvault_discovery/core/stealth.py
cloudvault_discovery/core/steganography.py
cloudvault_discovery/core/takeover.py
cloudvault_discovery/core/worker.py
cloudvault_discovery/providers/__init__.py
cloudvault_discovery/providers/aws_s3.py
cloudvault_discovery/providers/azure_blob.py
cloudvault_discovery/providers/gcp_storage.py
cloudvault4-1.0.1.dist-info/METADATA
cloudvault4-1.0.1.dist-info/WHEEL
cloudvault4-1.0.1.dist-info/entry_points.txt
cloudvault4-1.0.1.dist-info/top_level.txt
cloudvault4-1.0.1.dist-info/RECORD
