Metadata-Version: 2.4
Name: cloudvault4
Version: 1.0.1
Summary: Multi-cloud storage bucket discovery via certificate transparency monitoring
Author-email: ibrahimsql <ibrahimsql@proton.me>
License: MIT
Project-URL: Homepage, https://github.com/ibrahmsql/CloudVault
Project-URL: Bug Reports, https://github.com/ibrahmsql/CloudVault/issues
Project-URL: Source, https://github.com/ibrahmsql/CloudVault
Project-URL: Documentation, https://github.com/ibrahmsql/CloudVault#readme
Keywords: security,cloud,aws,s3,gcp,azure,blob-storage,bucket-discovery,certificate-transparency,reconnaissance
Classifier: Development Status :: 4 - Beta
Classifier: Intended Audience :: Information Technology
Classifier: Intended Audience :: System Administrators
Classifier: License :: OSI Approved :: MIT License
Classifier: Operating System :: OS Independent
Classifier: Programming Language :: Python :: 3
Classifier: Programming Language :: Python :: 3.8
Classifier: Programming Language :: Python :: 3.9
Classifier: Programming Language :: Python :: 3.10
Classifier: Programming Language :: Python :: 3.11
Classifier: Programming Language :: Python :: 3.12
Classifier: Topic :: Security
Classifier: Topic :: System :: Systems Administration
Classifier: Topic :: Internet :: WWW/HTTP
Requires-Python: >=3.8
Requires-Dist: requests>=2.28.0
Requires-Dist: pyyaml>=6.0
Requires-Dist: termcolor>=2.0.0
Requires-Dist: tldextract>=3.4.0
Requires-Dist: websockets>=10.0
Requires-Dist: fake-useragent>=1.4.0
Requires-Dist: dnspython>=2.2.0
Requires-Dist: pysocks>=1.7.1
Requires-Dist: cryptography>=3.4.8
Requires-Dist: python-magic>=0.4.27
Requires-Dist: psycopg2-binary>=2.9.0
Requires-Dist: pymongo>=4.0.0
Requires-Dist: mysql-connector-python>=8.0.0
Requires-Dist: slack-sdk>=3.19.0
Requires-Dist: paramiko>=3.0.0
Requires-Dist: pillow>=10.0.0
Requires-Dist: pypdf2>=3.0.0
Requires-Dist: python-nmap>=0.7.1
Requires-Dist: numpy>=1.24.0
Requires-Dist: colorama>=0.4.6
Requires-Dist: urllib3>=2.0.0
Requires-Dist: aiohttp>=3.8.0
Provides-Extra: aws
Requires-Dist: boto3>=1.26.0; extra == "aws"
Requires-Dist: botocore>=1.29.0; extra == "aws"
Provides-Extra: gcp
Requires-Dist: google-cloud-storage>=2.7.0; extra == "gcp"
Provides-Extra: azure
Requires-Dist: azure-storage-blob>=12.14.0; extra == "azure"
Provides-Extra: all
Requires-Dist: boto3>=1.26.0; extra == "all"
Requires-Dist: botocore>=1.29.0; extra == "all"
Requires-Dist: google-cloud-storage>=2.7.0; extra == "all"
Requires-Dist: azure-storage-blob>=12.14.0; extra == "all"
Provides-Extra: stealth
Requires-Dist: fake-useragent>=1.4.0; extra == "stealth"
Requires-Dist: dnspython>=2.2.0; extra == "stealth"
Requires-Dist: pysocks>=1.7.1; extra == "stealth"
Provides-Extra: exploit
Requires-Dist: cryptography>=3.4.8; extra == "exploit"
Requires-Dist: python-magic>=0.4.27; extra == "exploit"
Requires-Dist: psycopg2-binary>=2.9.0; extra == "exploit"
Requires-Dist: pymongo>=4.0.0; extra == "exploit"
Requires-Dist: mysql-connector-python>=8.0.0; extra == "exploit"
Requires-Dist: slack-sdk>=3.19.0; extra == "exploit"
Provides-Extra: full
Requires-Dist: boto3>=1.26.0; extra == "full"
Requires-Dist: botocore>=1.29.0; extra == "full"
Requires-Dist: google-cloud-storage>=2.7.0; extra == "full"
Requires-Dist: azure-storage-blob>=12.14.0; extra == "full"
Requires-Dist: fake-useragent>=1.4.0; extra == "full"
Requires-Dist: dnspython>=2.2.0; extra == "full"
Requires-Dist: pysocks>=1.7.1; extra == "full"
Requires-Dist: cryptography>=3.4.8; extra == "full"
Requires-Dist: python-magic>=0.4.27; extra == "full"
Requires-Dist: psycopg2-binary>=2.9.0; extra == "full"
Requires-Dist: pymongo>=4.0.0; extra == "full"
Requires-Dist: mysql-connector-python>=8.0.0; extra == "full"
Requires-Dist: slack-sdk>=3.19.0; extra == "full"
Provides-Extra: dev
Requires-Dist: pytest>=7.0.0; extra == "dev"
Requires-Dist: pytest-cov>=4.0.0; extra == "dev"
Requires-Dist: pytest-mock>=3.10.0; extra == "dev"
Requires-Dist: black>=22.0.0; extra == "dev"
Requires-Dist: flake8>=5.0.0; extra == "dev"
Requires-Dist: mypy>=1.0.0; extra == "dev"
